setup.py
baskt/__init__.py
baskt/baskt.py
baskt/version.py
baskt.egg-info/PKG-INFO
baskt.egg-info/SOURCES.txt
baskt.egg-info/dependency_links.txt
baskt.egg-info/requires.txt
baskt.egg-info/top_level.txt
baskt/test/__init__.py
baskt/test/test_baskt.py