Metadata-Version: 1.1
Name: baskt
Version: 0.0.5
Summary: This library allows you to quickly and easily use the Baskt API via Python.
Home-page: https://github.com/baskt/baskt-python
Author: Baskt Development Team
Author-email: hello@baskt.xyz
License: MIT
Platform: UNKNOWN
Classifier: Programming Language :: Python
Classifier: Intended Audience :: Developers
Classifier: Topic :: Database
